{"scientific_name": "Macrolepiota mastoidea", "gbif_id": 2536707, "common_names": {"eng": ["Slender parasol"], "dan": ["Puklet kæmpeparasolhat"], "deu": ["Zitzen-schirmpilz"], "eus": ["Maluta-puntadun", "Galanperna puntadun", "Galanperna puntaduna"], "spa": ["Lepiota amamelonada", "Lepiota mamelonada"], "fin": ["Suippu-ukonsieni"], "nld": ["Tepelparasolzwam", "Donkere parasolzwam"], "swe": ["Puckelfjällskivling", "Stjärnfjällskivling", "Vårtfjällskivling"], "nob": ["Skjoldparasollsopp"], "nno": ["Skjoldparasollsopp"], "cym": ["Parasol main"]}, "features": {"hymenium": ["gills"], "cap": ["umbonate", "flat"], "attachment": ["free"], "stipe": ["ring"], "print": ["white", "cream"], "ecology": ["saprotrophic"], "edibility": ["edible"]}}